py_rules/__init__.py
py_rules/__version__.py
py_rules/components.py
py_rules/condition.py
py_rules/constants.py
py_rules/engine.py
py_rules/errors.py
py_rules/parser.py
py_rules/storages.py
py_rules/utils.py
py_rules_engine-0.3.0.dist-info/LICENSE
py_rules_engine-0.3.0.dist-info/METADATA
py_rules_engine-0.3.0.dist-info/WHEEL
py_rules_engine-0.3.0.dist-info/top_level.txt
py_rules_engine-0.3.0.dist-info/RECORD
